CHANGELOG.md
CONTRIBUTORS.txt
LICENSE
MANIFEST.in
README.md
pyproject.toml
setup.cfg
setup.py
aioredis3/__init__.py
aioredis3/async_timeout.py
aioredis3/client.py
aioredis3/compat.py
aioredis3/connection.py
aioredis3/exceptions.py
aioredis3/lock.py
aioredis3/log.py
aioredis3/py.typed
aioredis3/sentinel.py
aioredis3/utils.py
aioredis3.egg-info/PKG-INFO
aioredis3.egg-info/SOURCES.txt
aioredis3.egg-info/dependency_links.txt
aioredis3.egg-info/requires.txt
aioredis3.egg-info/top_level.txt
tests/__init__.py
tests/compat.py
tests/conftest.py
tests/test_commands.py
tests/test_connection.py
tests/test_connection_pool.py
tests/test_encoding.py
tests/test_lock.py
tests/test_monitor.py
tests/test_multiprocessing.py
tests/test_pipeline.py
tests/test_pubsub.py
tests/test_scripting.py
tests/test_sentinel.py